odoo8_addon_product_custom_info-8.0.1.0.0-py2.7-nspkg.pth
odoo_addons/product_custom_info/__openerp__.py
odoo_addons/product_custom_info/__init__.py
odoo_addons/product_custom_info/README.rst
odoo_addons/product_custom_info/security/ir.model.access.csv
odoo_addons/product_custom_info/models/product_custom_info.py
odoo_addons/product_custom_info/models/__init__.py
odoo_addons/product_custom_info/i18n/es.po
odoo_addons/product_custom_info/views/product_view.xml
odoo8_addon_product_custom_info-8.0.1.0.0.dist-info/top_level.txt
odoo8_addon_product_custom_info-8.0.1.0.0.dist-info/WHEEL
odoo8_addon_product_custom_info-8.0.1.0.0.dist-info/RECORD
odoo8_addon_product_custom_info-8.0.1.0.0.dist-info/metadata.json
odoo8_addon_product_custom_info-8.0.1.0.0.dist-info/DESCRIPTION.rst
odoo8_addon_product_custom_info-8.0.1.0.0.dist-info/METADATA
odoo8_addon_product_custom_info-8.0.1.0.0.dist-info/namespace_packages.txt
